kahypar.cpython-312-x86_64-linux-gnu.so
kahypar-1.3.5.dist-info/LICENSE.txt
kahypar-1.3.5.dist-info/WHEEL
kahypar-1.3.5.dist-info/top_level.txt
kahypar-1.3.5.dist-info/COPYING
kahypar-1.3.5.dist-info/RECORD
kahypar-1.3.5.dist-info/AUTHORS
kahypar-1.3.5.dist-info/METADATA
kahypar.libs/libboost_program_options-d3219ad8.so.1.69.0
