Metadata-Version: 2.1
Name: kahypar
Version: 1.3.5
Summary: Python Inferface for the Karlsruhe Hypergraph Partitioning Framework (KaHyPar)
Home-page: https://www.kahypar.org
Author: Sebastian Schlag
Author-email: kahypar@sebastianschlag.de
Classifier: Development Status :: 5 - Production/Stable
Classifier: Topic :: Scientific/Engineering
Classifier: Topic :: Software Development :: Libraries :: Python Modules
Classifier: License :: OSI Approved :: GNU General Public License v3 or later (GPLv3+)
License-File: LICENSE.txt
License-File: COPYING
License-File: AUTHORS
